{
 "1" : {"ID" : 1 ,"Fname" : "赵"  },
 "2" : {"ID" : 2 ,"Fname" : "钱"  },
 "3" : {"ID" : 3 ,"Fname" : "孙"  },
 "4" : {"ID" : 4 ,"Fname" : "李"  },
 "5" : {"ID" : 5 ,"Fname" : "周"  },
 "6" : {"ID" : 6 ,"Fname" : "吴"  },
 "7" : {"ID" : 7 ,"Fname" : "郑"  },
 "8" : {"ID" : 8 ,"Fname" : "王"  },
 "9" : {"ID" : 9 ,"Fname" : "冯"  },
 "10" : {"ID" : 10 ,"Fname" : "陈"  },
 "11" : {"ID" : 11 ,"Fname" : "褚"  },
 "12" : {"ID" : 12 ,"Fname" : "卫"  },
 "13" : {"ID" : 13 ,"Fname" : "蒋"  },
 "14" : {"ID" : 14 ,"Fname" : "沈"  },
 "15" : {"ID" : 15 ,"Fname" : "韩"  },
 "16" : {"ID" : 16 ,"Fname" : "杨"  },
 "17" : {"ID" : 17 ,"Fname" : "朱"  },
 "18" : {"ID" : 18 ,"Fname" : "秦"  },
 "19" : {"ID" : 19 ,"Fname" : "尤"  },
 "20" : {"ID" : 20 ,"Fname" : "许"  },
 "21" : {"ID" : 21 ,"Fname" : "何"  },
 "22" : {"ID" : 22 ,"Fname" : "吕"  },
 "23" : {"ID" : 23 ,"Fname" : "施"  },
 "24" : {"ID" : 24 ,"Fname" : "张"  },
 "25" : {"ID" : 25 ,"Fname" : "孔"  },
 "26" : {"ID" : 26 ,"Fname" : "曹"  },
 "27" : {"ID" : 27 ,"Fname" : "严"  },
 "28" : {"ID" : 28 ,"Fname" : "华"  },
 "29" : {"ID" : 29 ,"Fname" : "金"  },
 "30" : {"ID" : 30 ,"Fname" : "魏"  },
 "31" : {"ID" : 31 ,"Fname" : "陶"  },
 "32" : {"ID" : 32 ,"Fname" : "姜"  },
 "33" : {"ID" : 33 ,"Fname" : "戚"  },
 "34" : {"ID" : 34 ,"Fname" : "谢"  },
 "35" : {"ID" : 35 ,"Fname" : "邹"  },
 "36" : {"ID" : 36 ,"Fname" : "喻"  },
 "37" : {"ID" : 37 ,"Fname" : "柏"  },
 "38" : {"ID" : 38 ,"Fname" : "水"  },
 "39" : {"ID" : 39 ,"Fname" : "窦"  },
 "40" : {"ID" : 40 ,"Fname" : "章"  },
 "41" : {"ID" : 41 ,"Fname" : "云"  },
 "42" : {"ID" : 42 ,"Fname" : "苏"  },
 "43" : {"ID" : 43 ,"Fname" : "潘"  },
 "44" : {"ID" : 44 ,"Fname" : "葛"  },
 "45" : {"ID" : 45 ,"Fname" : "奚"  },
 "46" : {"ID" : 46 ,"Fname" : "范"  },
 "47" : {"ID" : 47 ,"Fname" : "彭"  },
 "48" : {"ID" : 48 ,"Fname" : "郎"  },
 "49" : {"ID" : 49 ,"Fname" : "鲁"  },
 "50" : {"ID" : 50 ,"Fname" : "韦"  },
 "51" : {"ID" : 51 ,"Fname" : "昌"  },
 "52" : {"ID" : 52 ,"Fname" : "马"  },
 "53" : {"ID" : 53 ,"Fname" : "苗"  },
 "54" : {"ID" : 54 ,"Fname" : "凤"  },
 "55" : {"ID" : 55 ,"Fname" : "花"  },
 "56" : {"ID" : 56 ,"Fname" : "方"  },
 "57" : {"ID" : 57 ,"Fname" : "俞"  },
 "58" : {"ID" : 58 ,"Fname" : "任"  },
 "59" : {"ID" : 59 ,"Fname" : "袁"  },
 "60" : {"ID" : 60 ,"Fname" : "柳"  },
 "61" : {"ID" : 61 ,"Fname" : "邓"  },
 "62" : {"ID" : 62 ,"Fname" : "鲍"  },
 "63" : {"ID" : 63 ,"Fname" : "史"  },
 "64" : {"ID" : 64 ,"Fname" : "唐"  },
 "65" : {"ID" : 65 ,"Fname" : "费"  },
 "66" : {"ID" : 66 ,"Fname" : "廉"  },
 "67" : {"ID" : 67 ,"Fname" : "岑"  },
 "68" : {"ID" : 68 ,"Fname" : "薛"  },
 "69" : {"ID" : 69 ,"Fname" : "雷"  },
 "70" : {"ID" : 70 ,"Fname" : "贺"  },
 "71" : {"ID" : 71 ,"Fname" : "倪"  },
 "72" : {"ID" : 72 ,"Fname" : "汤"  },
 "73" : {"ID" : 73 ,"Fname" : "藤"  },
 "74" : {"ID" : 74 ,"Fname" : "殷"  },
 "75" : {"ID" : 75 ,"Fname" : "罗"  },
 "76" : {"ID" : 76 ,"Fname" : "毕"  },
 "77" : {"ID" : 77 ,"Fname" : "郝"  },
 "78" : {"ID" : 78 ,"Fname" : "邬"  },
 "79" : {"ID" : 79 ,"Fname" : "安"  },
 "80" : {"ID" : 80 ,"Fname" : "常"  },
 "81" : {"ID" : 81 ,"Fname" : "乐"  },
 "82" : {"ID" : 82 ,"Fname" : "于"  },
 "83" : {"ID" : 83 ,"Fname" : "时"  },
 "84" : {"ID" : 84 ,"Fname" : "付"  },
 "85" : {"ID" : 85 ,"Fname" : "皮"  },
 "86" : {"ID" : 86 ,"Fname" : "卞"  },
 "87" : {"ID" : 87 ,"Fname" : "齐"  },
 "88" : {"ID" : 88 ,"Fname" : "康"  },
 "89" : {"ID" : 89 ,"Fname" : "伍"  },
 "90" : {"ID" : 90 ,"Fname" : "余"  },
 "91" : {"ID" : 91 ,"Fname" : "元"  },
 "92" : {"ID" : 92 ,"Fname" : "卜"  },
 "93" : {"ID" : 93 ,"Fname" : "顾"  },
 "94" : {"ID" : 94 ,"Fname" : "孟"  },
 "95" : {"ID" : 95 ,"Fname" : "平"  },
 "96" : {"ID" : 96 ,"Fname" : "黄"  },
 "97" : {"ID" : 97 ,"Fname" : "和"  },
 "98" : {"ID" : 98 ,"Fname" : "穆"  },
 "99" : {"ID" : 99 ,"Fname" : "肖"  },
 "100" : {"ID" : 100 ,"Fname" : "尹"  },
 "101" : {"ID" : 101 ,"Fname" : "姚"  },
 "102" : {"ID" : 102 ,"Fname" : "邵"  },
 "103" : {"ID" : 103 ,"Fname" : "湛"  },
 "104" : {"ID" : 104 ,"Fname" : "汪"  },
 "105" : {"ID" : 105 ,"Fname" : "祁"  },
 "106" : {"ID" : 106 ,"Fname" : "毛"  },
 "107" : {"ID" : 107 ,"Fname" : "禹"  },
 "108" : {"ID" : 108 ,"Fname" : "狄"  },
 "109" : {"ID" : 109 ,"Fname" : "米"  },
 "110" : {"ID" : 110 ,"Fname" : "贝"  },
 "111" : {"ID" : 111 ,"Fname" : "明"  },
 "112" : {"ID" : 112 ,"Fname" : "藏"  },
 "113" : {"ID" : 113 ,"Fname" : "计"  },
 "114" : {"ID" : 114 ,"Fname" : "伏"  },
 "115" : {"ID" : 115 ,"Fname" : "成"  },
 "116" : {"ID" : 116 ,"Fname" : "戴"  },
 "117" : {"ID" : 117 ,"Fname" : "谈"  },
 "118" : {"ID" : 118 ,"Fname" : "宋"  },
 "119" : {"ID" : 119 ,"Fname" : "茅"  },
 "120" : {"ID" : 120 ,"Fname" : "庞"  },
 "121" : {"ID" : 121 ,"Fname" : "熊"  },
 "122" : {"ID" : 122 ,"Fname" : "纪"  },
 "123" : {"ID" : 123 ,"Fname" : "舒"  },
 "124" : {"ID" : 124 ,"Fname" : "屈"  },
 "125" : {"ID" : 125 ,"Fname" : "项"  },
 "126" : {"ID" : 126 ,"Fname" : "祝"  },
 "127" : {"ID" : 127 ,"Fname" : "董"  },
 "128" : {"ID" : 128 ,"Fname" : "梁"  },
 "129" : {"ID" : 129 ,"Fname" : "杜"  },
 "130" : {"ID" : 130 ,"Fname" : "阮"  },
 "131" : {"ID" : 131 ,"Fname" : "蓝"  },
 "132" : {"ID" : 132 ,"Fname" : "闵"  },
 "133" : {"ID" : 133 ,"Fname" : "席"  },
 "134" : {"ID" : 134 ,"Fname" : "季"  },
 "135" : {"ID" : 135 ,"Fname" : "麻"  },
 "136" : {"ID" : 136 ,"Fname" : "强"  },
 "137" : {"ID" : 137 ,"Fname" : "贾"  },
 "138" : {"ID" : 138 ,"Fname" : "路"  },
 "139" : {"ID" : 139 ,"Fname" : "娄"  },
 "140" : {"ID" : 140 ,"Fname" : "危"  },
 "141" : {"ID" : 141 ,"Fname" : "江"  },
 "142" : {"ID" : 142 ,"Fname" : "童"  },
 "143" : {"ID" : 143 ,"Fname" : "颜"  },
 "144" : {"ID" : 144 ,"Fname" : "郭"  },
 "145" : {"ID" : 145 ,"Fname" : "梅"  },
 "146" : {"ID" : 146 ,"Fname" : "盛"  },
 "147" : {"ID" : 147 ,"Fname" : "林"  },
 "148" : {"ID" : 148 ,"Fname" : "刁"  },
 "149" : {"ID" : 149 ,"Fname" : "钟"  },
 "150" : {"ID" : 150 ,"Fname" : "徐"  },
 "151" : {"ID" : 151 ,"Fname" : "邱"  },
 "152" : {"ID" : 152 ,"Fname" : "骆"  },
 "153" : {"ID" : 153 ,"Fname" : "高"  },
 "154" : {"ID" : 154 ,"Fname" : "夏"  },
 "155" : {"ID" : 155 ,"Fname" : "蔡"  },
 "156" : {"ID" : 156 ,"Fname" : "田"  },
 "157" : {"ID" : 157 ,"Fname" : "樊"  },
 "158" : {"ID" : 158 ,"Fname" : "胡"  },
 "159" : {"ID" : 159 ,"Fname" : "凌"  },
 "160" : {"ID" : 160 ,"Fname" : "霍"  },
 "161" : {"ID" : 161 ,"Fname" : "虞"  },
 "162" : {"ID" : 162 ,"Fname" : "万"  },
 "163" : {"ID" : 163 ,"Fname" : "支"  },
 "164" : {"ID" : 164 ,"Fname" : "柯"  },
 "165" : {"ID" : 165 ,"Fname" : "昝"  },
 "166" : {"ID" : 166 ,"Fname" : "管"  },
 "167" : {"ID" : 167 ,"Fname" : "卢"  },
 "168" : {"ID" : 168 ,"Fname" : "莫"  },
 "169" : {"ID" : 169 ,"Fname" : "经"  },
 "170" : {"ID" : 170 ,"Fname" : "房"  },
 "171" : {"ID" : 171 ,"Fname" : "裘"  },
 "172" : {"ID" : 172 ,"Fname" : "缪"  },
 "173" : {"ID" : 173 ,"Fname" : "干"  },
 "174" : {"ID" : 174 ,"Fname" : "解"  },
 "175" : {"ID" : 175 ,"Fname" : "应"  },
 "176" : {"ID" : 176 ,"Fname" : "宗"  },
 "177" : {"ID" : 177 ,"Fname" : "丁"  },
 "178" : {"ID" : 178 ,"Fname" : "宣"  },
 "179" : {"ID" : 179 ,"Fname" : "贲"  },
 "180" : {"ID" : 180 ,"Fname" : "郁"  },
 "181" : {"ID" : 181 ,"Fname" : "单"  },
 "182" : {"ID" : 182 ,"Fname" : "杭"  },
 "183" : {"ID" : 183 ,"Fname" : "洪"  },
 "184" : {"ID" : 184 ,"Fname" : "包"  },
 "185" : {"ID" : 185 ,"Fname" : "诸"  },
 "186" : {"ID" : 186 ,"Fname" : "左"  },
 "187" : {"ID" : 187 ,"Fname" : "石"  },
 "188" : {"ID" : 188 ,"Fname" : "崔"  },
 "189" : {"ID" : 189 ,"Fname" : "吉"  },
 "190" : {"ID" : 190 ,"Fname" : "钮"  },
 "191" : {"ID" : 191 ,"Fname" : "龚"  },
 "192" : {"ID" : 192 ,"Fname" : "程"  },
 "193" : {"ID" : 193 ,"Fname" : "嵇"  },
 "194" : {"ID" : 194 ,"Fname" : "邢"  },
 "195" : {"ID" : 195 ,"Fname" : "滑"  },
 "196" : {"ID" : 196 ,"Fname" : "裴"  },
 "197" : {"ID" : 197 ,"Fname" : "陆"  },
 "198" : {"ID" : 198 ,"Fname" : "荣"  },
 "199" : {"ID" : 199 ,"Fname" : "翁"  },
 "200" : {"ID" : 200 ,"Fname" : "荀"  },
 "201" : {"ID" : 201 ,"Fname" : "羊"  },
 "202" : {"ID" : 202 ,"Fname" : "惠"  },
 "203" : {"ID" : 203 ,"Fname" : "甄"  },
 "204" : {"ID" : 204 ,"Fname" : "曲"  },
 "205" : {"ID" : 205 ,"Fname" : "家"  },
 "206" : {"ID" : 206 ,"Fname" : "封"  },
 "207" : {"ID" : 207 ,"Fname" : "芮"  },
 "208" : {"ID" : 208 ,"Fname" : "羿"  },
 "209" : {"ID" : 209 ,"Fname" : "储"  },
 "210" : {"ID" : 210 ,"Fname" : "靳"  },
 "211" : {"ID" : 211 ,"Fname" : "汲"  },
 "212" : {"ID" : 212 ,"Fname" : "邴"  },
 "213" : {"ID" : 213 ,"Fname" : "糜"  },
 "214" : {"ID" : 214 ,"Fname" : "松"  },
 "215" : {"ID" : 215 ,"Fname" : "井"  },
 "216" : {"ID" : 216 ,"Fname" : "段"  },
 "217" : {"ID" : 217 ,"Fname" : "富"  },
 "218" : {"ID" : 218 ,"Fname" : "巫"  },
 "219" : {"ID" : 219 ,"Fname" : "乌"  },
 "220" : {"ID" : 220 ,"Fname" : "焦"  },
 "221" : {"ID" : 221 ,"Fname" : "巴"  },
 "222" : {"ID" : 222 ,"Fname" : "弓"  },
 "223" : {"ID" : 223 ,"Fname" : "牧"  },
 "224" : {"ID" : 224 ,"Fname" : "隗"  },
 "225" : {"ID" : 225 ,"Fname" : "山"  },
 "226" : {"ID" : 226 ,"Fname" : "谷"  },
 "227" : {"ID" : 227 ,"Fname" : "车"  },
 "228" : {"ID" : 228 ,"Fname" : "侯"  },
 "229" : {"ID" : 229 ,"Fname" : "宓"  },
 "230" : {"ID" : 230 ,"Fname" : "蓬"  },
 "231" : {"ID" : 231 ,"Fname" : "全"  },
 "232" : {"ID" : 232 ,"Fname" : "郗"  },
 "233" : {"ID" : 233 ,"Fname" : "班"  },
 "234" : {"ID" : 234 ,"Fname" : "仰"  },
 "235" : {"ID" : 235 ,"Fname" : "秋"  },
 "236" : {"ID" : 236 ,"Fname" : "仲"  },
 "237" : {"ID" : 237 ,"Fname" : "伊"  },
 "238" : {"ID" : 238 ,"Fname" : "宫"  },
 "239" : {"ID" : 239 ,"Fname" : "宁"  },
 "240" : {"ID" : 240 ,"Fname" : "仇"  },
 "241" : {"ID" : 241 ,"Fname" : "栾"  },
 "242" : {"ID" : 242 ,"Fname" : "暴"  },
 "243" : {"ID" : 243 ,"Fname" : "甘"  },
 "244" : {"ID" : 244 ,"Fname" : "钭"  },
 "245" : {"ID" : 245 ,"Fname" : "厉"  },
 "246" : {"ID" : 246 ,"Fname" : "戎"  },
 "247" : {"ID" : 247 ,"Fname" : "祖"  },
 "248" : {"ID" : 248 ,"Fname" : "武"  },
 "249" : {"ID" : 249 ,"Fname" : "符"  },
 "250" : {"ID" : 250 ,"Fname" : "刘"  },
 "251" : {"ID" : 251 ,"Fname" : "景"  },
 "252" : {"ID" : 252 ,"Fname" : "詹"  },
 "253" : {"ID" : 253 ,"Fname" : "束"  },
 "254" : {"ID" : 254 ,"Fname" : "龙"  },
 "255" : {"ID" : 255 ,"Fname" : "叶"  },
 "256" : {"ID" : 256 ,"Fname" : "幸"  },
 "257" : {"ID" : 257 ,"Fname" : "司"  },
 "258" : {"ID" : 258 ,"Fname" : "韶"  },
 "259" : {"ID" : 259 ,"Fname" : "郜"  },
 "260" : {"ID" : 260 ,"Fname" : "黎"  },
 "261" : {"ID" : 261 ,"Fname" : "蓟"  },
 "262" : {"ID" : 262 ,"Fname" : "薄"  },
 "263" : {"ID" : 263 ,"Fname" : "印"  },
 "264" : {"ID" : 264 ,"Fname" : "宿"  },
 "265" : {"ID" : 265 ,"Fname" : "白"  },
 "266" : {"ID" : 266 ,"Fname" : "怀"  },
 "267" : {"ID" : 267 ,"Fname" : "蒲"  },
 "268" : {"ID" : 268 ,"Fname" : "邰"  },
 "269" : {"ID" : 269 ,"Fname" : "从"  },
 "270" : {"ID" : 270 ,"Fname" : "鄂"  },
 "271" : {"ID" : 271 ,"Fname" : "索"  },
 "272" : {"ID" : 272 ,"Fname" : "咸"  },
 "273" : {"ID" : 273 ,"Fname" : "籍"  },
 "274" : {"ID" : 274 ,"Fname" : "赖"  },
 "275" : {"ID" : 275 ,"Fname" : "卓"  },
 "276" : {"ID" : 276 ,"Fname" : "蔺"  },
 "277" : {"ID" : 277 ,"Fname" : "屠"  },
 "278" : {"ID" : 278 ,"Fname" : "蒙"  },
 "279" : {"ID" : 279 ,"Fname" : "池"  },
 "280" : {"ID" : 280 ,"Fname" : "乔"  },
 "281" : {"ID" : 281 ,"Fname" : "阴"  },
 "282" : {"ID" : 282 ,"Fname" : "胥"  },
 "283" : {"ID" : 283 ,"Fname" : "能"  },
 "284" : {"ID" : 284 ,"Fname" : "苍"  },
 "285" : {"ID" : 285 ,"Fname" : "双"  },
 "286" : {"ID" : 286 ,"Fname" : "闻"  },
 "287" : {"ID" : 287 ,"Fname" : "莘"  },
 "288" : {"ID" : 288 ,"Fname" : "党"  },
 "289" : {"ID" : 289 ,"Fname" : "翟"  },
 "290" : {"ID" : 290 ,"Fname" : "谭"  },
 "291" : {"ID" : 291 ,"Fname" : "贡"  },
 "292" : {"ID" : 292 ,"Fname" : "劳"  },
 "293" : {"ID" : 293 ,"Fname" : "逄"  },
 "294" : {"ID" : 294 ,"Fname" : "姬"  },
 "295" : {"ID" : 295 ,"Fname" : "申"  },
 "296" : {"ID" : 296 ,"Fname" : "扶"  },
 "297" : {"ID" : 297 ,"Fname" : "堵"  },
 "298" : {"ID" : 298 ,"Fname" : "冉"  },
 "299" : {"ID" : 299 ,"Fname" : "宰"  },
 "300" : {"ID" : 300 ,"Fname" : "郦"  },
 "301" : {"ID" : 301 ,"Fname" : "雍"  },
 "302" : {"ID" : 302 ,"Fname" : "隙"  },
 "303" : {"ID" : 303 ,"Fname" : "璩"  },
 "304" : {"ID" : 304 ,"Fname" : "桑"  },
 "305" : {"ID" : 305 ,"Fname" : "桂"  },
 "306" : {"ID" : 306 ,"Fname" : "濮"  },
 "307" : {"ID" : 307 ,"Fname" : "牛"  },
 "308" : {"ID" : 308 ,"Fname" : "寿"  },
 "309" : {"ID" : 309 ,"Fname" : "通"  },
 "310" : {"ID" : 310 ,"Fname" : "边"  },
 "311" : {"ID" : 311 ,"Fname" : "扈"  },
 "312" : {"ID" : 312 ,"Fname" : "燕"  },
 "313" : {"ID" : 313 ,"Fname" : "冀"  },
 "314" : {"ID" : 314 ,"Fname" : "郏"  },
 "315" : {"ID" : 315 ,"Fname" : "浦"  },
 "316" : {"ID" : 316 ,"Fname" : "尚"  },
 "317" : {"ID" : 317 ,"Fname" : "农"  },
 "318" : {"ID" : 318 ,"Fname" : "温"  },
 "319" : {"ID" : 319 ,"Fname" : "别"  },
 "320" : {"ID" : 320 ,"Fname" : "庄"  },
 "321" : {"ID" : 321 ,"Fname" : "晏"  },
 "322" : {"ID" : 322 ,"Fname" : "柴"  },
 "323" : {"ID" : 323 ,"Fname" : "瞿"  },
 "324" : {"ID" : 324 ,"Fname" : "阎"  },
 "325" : {"ID" : 325 ,"Fname" : "充"  },
 "326" : {"ID" : 326 ,"Fname" : "慕"  },
 "327" : {"ID" : 327 ,"Fname" : "连"  },
 "328" : {"ID" : 328 ,"Fname" : "茹"  },
 "329" : {"ID" : 329 ,"Fname" : "习"  },
 "330" : {"ID" : 330 ,"Fname" : "宦"  },
 "331" : {"ID" : 331 ,"Fname" : "艾"  },
 "332" : {"ID" : 332 ,"Fname" : "鱼"  },
 "333" : {"ID" : 333 ,"Fname" : "容"  },
 "334" : {"ID" : 334 ,"Fname" : "向"  },
 "335" : {"ID" : 335 ,"Fname" : "古"  },
 "336" : {"ID" : 336 ,"Fname" : "易"  },
 "337" : {"ID" : 337 ,"Fname" : "慎"  },
 "338" : {"ID" : 338 ,"Fname" : "戈"  },
 "339" : {"ID" : 339 ,"Fname" : "廖"  },
 "340" : {"ID" : 340 ,"Fname" : "庾"  },
 "341" : {"ID" : 341 ,"Fname" : "终"  },
 "342" : {"ID" : 342 ,"Fname" : "暨"  },
 "343" : {"ID" : 343 ,"Fname" : "居"  },
 "344" : {"ID" : 344 ,"Fname" : "衡"  },
 "345" : {"ID" : 345 ,"Fname" : "步"  },
 "346" : {"ID" : 346 ,"Fname" : "都"  },
 "347" : {"ID" : 347 ,"Fname" : "耿"  },
 "348" : {"ID" : 348 ,"Fname" : "满"  },
 "349" : {"ID" : 349 ,"Fname" : "弘"  },
 "350" : {"ID" : 350 ,"Fname" : "匡"  },
 "351" : {"ID" : 351 ,"Fname" : "文"  },
 "352" : {"ID" : 352 ,"Fname" : "国"  },
 "353" : {"ID" : 353 ,"Fname" : "寇"  },
 "354" : {"ID" : 354 ,"Fname" : "广"  },
 "355" : {"ID" : 355 ,"Fname" : "禄"  },
 "356" : {"ID" : 356 ,"Fname" : "阙"  },
 "357" : {"ID" : 357 ,"Fname" : "东"  },
 "358" : {"ID" : 358 ,"Fname" : "欧"  },
 "359" : {"ID" : 359 ,"Fname" : "殳"  },
 "360" : {"ID" : 360 ,"Fname" : "沃"  },
 "361" : {"ID" : 361 ,"Fname" : "利"  },
 "362" : {"ID" : 362 ,"Fname" : "蔚"  },
 "363" : {"ID" : 363 ,"Fname" : "越"  },
 "364" : {"ID" : 364 ,"Fname" : "夔"  },
 "365" : {"ID" : 365 ,"Fname" : "隆"  },
 "366" : {"ID" : 366 ,"Fname" : "师"  },
 "367" : {"ID" : 367 ,"Fname" : "巩"  },
 "368" : {"ID" : 368 ,"Fname" : "厍"  },
 "369" : {"ID" : 369 ,"Fname" : "聂"  },
 "370" : {"ID" : 370 ,"Fname" : "晁"  },
 "371" : {"ID" : 371 ,"Fname" : "勾"  },
 "372" : {"ID" : 372 ,"Fname" : "敖"  },
 "373" : {"ID" : 373 ,"Fname" : "融"  },
 "374" : {"ID" : 374 ,"Fname" : "冷"  },
 "375" : {"ID" : 375 ,"Fname" : "訾"  },
 "376" : {"ID" : 376 ,"Fname" : "辛"  },
 "377" : {"ID" : 377 ,"Fname" : "阚"  },
 "378" : {"ID" : 378 ,"Fname" : "那"  },
 "379" : {"ID" : 379 ,"Fname" : "简"  },
 "380" : {"ID" : 380 ,"Fname" : "饶"  },
 "381" : {"ID" : 381 ,"Fname" : "空"  },
 "382" : {"ID" : 382 ,"Fname" : "曾"  },
 "383" : {"ID" : 383 ,"Fname" : "毋"  },
 "384" : {"ID" : 384 ,"Fname" : "沙"  },
 "385" : {"ID" : 385 ,"Fname" : "乜"  },
 "386" : {"ID" : 386 ,"Fname" : "养"  },
 "387" : {"ID" : 387 ,"Fname" : "鞠"  },
 "388" : {"ID" : 388 ,"Fname" : "须"  },
 "389" : {"ID" : 389 ,"Fname" : "丰"  },
 "390" : {"ID" : 390 ,"Fname" : "巢"  },
 "391" : {"ID" : 391 ,"Fname" : "关"  },
 "392" : {"ID" : 392 ,"Fname" : "蒯"  },
 "393" : {"ID" : 393 ,"Fname" : "相"  },
 "394" : {"ID" : 394 ,"Fname" : "查"  },
 "395" : {"ID" : 395 ,"Fname" : "后"  },
 "396" : {"ID" : 396 ,"Fname" : "荆"  },
 "397" : {"ID" : 397 ,"Fname" : "红"  },
 "398" : {"ID" : 398 ,"Fname" : "游"  },
 "399" : {"ID" : 399 ,"Fname" : "竺"  },
 "400" : {"ID" : 400 ,"Fname" : "权"  },
 "401" : {"ID" : 401 ,"Fname" : "逯"  },
 "402" : {"ID" : 402 ,"Fname" : "盖"  },
 "403" : {"ID" : 403 ,"Fname" : "益"  },
 "404" : {"ID" : 404 ,"Fname" : "桓"  },
 "405" : {"ID" : 405 ,"Fname" : "公"  },
 "406" : {"ID" : 406 ,"Fname" : "俟"  },
 "407" : {"ID" : 407 ,"Fname" : "上官"  },
 "408" : {"ID" : 408 ,"Fname" : "欧阳"  },
 "409" : {"ID" : 409 ,"Fname" : "夏候"  },
 "410" : {"ID" : 410 ,"Fname" : "诸葛"  },
 "411" : {"ID" : 411 ,"Fname" : "闻人"  },
 "412" : {"ID" : 412 ,"Fname" : "东方"  },
 "413" : {"ID" : 413 ,"Fname" : "赫连"  },
 "414" : {"ID" : 414 ,"Fname" : "皇甫"  },
 "415" : {"ID" : 415 ,"Fname" : "尉迟"  },
 "416" : {"ID" : 416 ,"Fname" : "公羊"  },
 "417" : {"ID" : 417 ,"Fname" : "澹台"  },
 "418" : {"ID" : 418 ,"Fname" : "公冶"  },
 "419" : {"ID" : 419 ,"Fname" : "宗政"  },
 "420" : {"ID" : 420 ,"Fname" : "濮阳"  },
 "421" : {"ID" : 421 ,"Fname" : "淳于"  },
 "422" : {"ID" : 422 ,"Fname" : "单于"  },
 "423" : {"ID" : 423 ,"Fname" : "太叔"  },
 "424" : {"ID" : 424 ,"Fname" : "申屠"  },
 "425" : {"ID" : 425 ,"Fname" : "公孙"  },
 "426" : {"ID" : 426 ,"Fname" : "仲孙"  },
 "427" : {"ID" : 427 ,"Fname" : "轩辕"  },
 "428" : {"ID" : 428 ,"Fname" : "令狐"  },
 "429" : {"ID" : 429 ,"Fname" : "钟离"  },
 "430" : {"ID" : 430 ,"Fname" : "宇文"  },
 "431" : {"ID" : 431 ,"Fname" : "长孙"  },
 "432" : {"ID" : 432 ,"Fname" : "慕容"  },
 "433" : {"ID" : 433 ,"Fname" : "鲜于"  },
 "434" : {"ID" : 434 ,"Fname" : "闾丘"  },
 "435" : {"ID" : 435 ,"Fname" : "司徒"  },
 "436" : {"ID" : 436 ,"Fname" : "司空"  },
 "437" : {"ID" : 437 ,"Fname" : "亓官"  },
 "438" : {"ID" : 438 ,"Fname" : "司寇"  },
 "439" : {"ID" : 439 ,"Fname" : "仉督"  },
 "440" : {"ID" : 440 ,"Fname" : "子车"  },
 "441" : {"ID" : 441 ,"Fname" : "颛孙"  },
 "442" : {"ID" : 442 ,"Fname" : "端木"  },
 "443" : {"ID" : 443 ,"Fname" : "巫马"  },
 "444" : {"ID" : 444 ,"Fname" : "公西"  },
 "445" : {"ID" : 445 ,"Fname" : "漆雕"  },
 "446" : {"ID" : 446 ,"Fname" : "乐正"  },
 "447" : {"ID" : 447 ,"Fname" : "壤驷"  },
 "448" : {"ID" : 448 ,"Fname" : "公良"  },
 "449" : {"ID" : 449 ,"Fname" : "拓拔"  },
 "450" : {"ID" : 450 ,"Fname" : "夹谷"  },
 "451" : {"ID" : 451 ,"Fname" : "宰父"  },
 "452" : {"ID" : 452 ,"Fname" : "谷梁"  },
 "453" : {"ID" : 453 ,"Fname" : "楚"  },
 "454" : {"ID" : 454 ,"Fname" : "晋"  },
 "455" : {"ID" : 455 ,"Fname" : "闫"  },
 "456" : {"ID" : 456 ,"Fname" : "法"  },
 "457" : {"ID" : 457 ,"Fname" : "汝"  },
 "458" : {"ID" : 458 ,"Fname" : "鄢"  },
 "459" : {"ID" : 459 ,"Fname" : "涂"  },
 "460" : {"ID" : 460 ,"Fname" : "钦"  },
 "461" : {"ID" : 461 ,"Fname" : "段干"  },
 "462" : {"ID" : 462 ,"Fname" : "百里"  },
 "463" : {"ID" : 463 ,"Fname" : "东郭"  },
 "464" : {"ID" : 464 ,"Fname" : "南门"  },
 "465" : {"ID" : 465 ,"Fname" : "呼延"  },
 "466" : {"ID" : 466 ,"Fname" : "归海"  },
 "467" : {"ID" : 467 ,"Fname" : "羊舌"  },
 "468" : {"ID" : 468 ,"Fname" : "微生"  },
 "469" : {"ID" : 469 ,"Fname" : "岳"  },
 "470" : {"ID" : 470 ,"Fname" : "帅"  },
 "471" : {"ID" : 471 ,"Fname" : "缑"  },
 "472" : {"ID" : 472 ,"Fname" : "亢"  },
 "473" : {"ID" : 473 ,"Fname" : "况"  },
 "474" : {"ID" : 474 ,"Fname" : "有"  },
 "475" : {"ID" : 475 ,"Fname" : "琴"  },
 "476" : {"ID" : 476 ,"Fname" : "梁丘"  },
 "477" : {"ID" : 477 ,"Fname" : "左丘"  },
 "478" : {"ID" : 478 ,"Fname" : "东门"  },
 "479" : {"ID" : 479 ,"Fname" : "西门"  },
 "480" : {"ID" : 480 ,"Fname" : "商"  },
 "481" : {"ID" : 481 ,"Fname" : "牟"  },
 "482" : {"ID" : 482 ,"Fname" : "佘"  },
 "483" : {"ID" : 483 ,"Fname" : "耳"  },
 "484" : {"ID" : 484 ,"Fname" : "伯"  },
 "485" : {"ID" : 485 ,"Fname" : "赏"  },
 "486" : {"ID" : 486 ,"Fname" : "南宫"  },
 "487" : {"ID" : 487 ,"Fname" : "墨"  },
 "488" : {"ID" : 488 ,"Fname" : "哈"  },
 "489" : {"ID" : 489 ,"Fname" : "谯笪"  },
 "490" : {"ID" : 490 ,"Fname" : "年"  },
 "491" : {"ID" : 491 ,"Fname" : "爱"  },
 "492" : {"ID" : 492 ,"Fname" : "阳"  },
 "493" : {"ID" : 493 ,"Fname" : "佟"  },
 "494" : {"ID" : 494 ,"Fname" : "第五"  },
 "495" : {"ID" : 495 ,"Fname" : "言"  },
 "496" : {"ID" : 496 ,"Fname" : "司马"  }
}