{
 "1" : {"ID" : 1 ,"armyID" : 101 ,"num" : 10  },
 "2" : {"ID" : 2 ,"armyID" : 201 ,"num" : 10  },
 "3" : {"ID" : 3 ,"armyID" : 301 ,"num" : 10  },
 "4" : {"ID" : 4 ,"armyID" : 401 ,"num" : 10  },
 "5" : {"ID" : 5 ,"armyID" : 103 ,"num" : 1  },
 "6" : {"ID" : 6 ,"armyID" : 103 ,"num" : 5  },
 "7" : {"ID" : 7 ,"armyID" : 102 ,"num" : 2  },
 "401" : {"ID" : 401 ,"armyID" : 401 ,"num" : 1  },
 "402" : {"ID" : 402 ,"armyID" : 402 ,"num" : 1  },
 "403" : {"ID" : 403 ,"armyID" : 403 ,"num" : 1  },
 "404" : {"ID" : 404 ,"armyID" : 404 ,"num" : 1  },
 "405" : {"ID" : 405 ,"armyID" : 405 ,"num" : 1  },
 "406" : {"ID" : 406 ,"armyID" : 406 ,"num" : 1  },
 "407" : {"ID" : 407 ,"armyID" : 407 ,"num" : 1  },
 "408" : {"ID" : 408 ,"armyID" : 408 ,"num" : 1  },
 "409" : {"ID" : 409 ,"armyID" : 409 ,"num" : 1  },
 "410" : {"ID" : 410 ,"armyID" : 104 ,"num" : 100  },
 "411" : {"ID" : 411 ,"armyID" : 103 ,"num" : 18  },
 "412" : {"ID" : 412 ,"armyID" : 104 ,"num" : 50  },
 "301" : {"ID" : 301 ,"armyID" : 301 ,"num" : 1  },
 "302" : {"ID" : 302 ,"armyID" : 302 ,"num" : 1  },
 "303" : {"ID" : 303 ,"armyID" : 303 ,"num" : 1  },
 "304" : {"ID" : 304 ,"armyID" : 304 ,"num" : 1  },
 "305" : {"ID" : 305 ,"armyID" : 305 ,"num" : 1  },
 "306" : {"ID" : 306 ,"armyID" : 306 ,"num" : 1  },
 "307" : {"ID" : 307 ,"armyID" : 307 ,"num" : 1  },
 "308" : {"ID" : 308 ,"armyID" : 308 ,"num" : 1  },
 "309" : {"ID" : 309 ,"armyID" : 309 ,"num" : 1  },
 "201" : {"ID" : 201 ,"armyID" : 201 ,"num" : 1  },
 "202" : {"ID" : 202 ,"armyID" : 202 ,"num" : 1  },
 "203" : {"ID" : 203 ,"armyID" : 203 ,"num" : 1  },
 "204" : {"ID" : 204 ,"armyID" : 204 ,"num" : 1  },
 "205" : {"ID" : 205 ,"armyID" : 205 ,"num" : 1  },
 "206" : {"ID" : 206 ,"armyID" : 206 ,"num" : 1  },
 "207" : {"ID" : 207 ,"armyID" : 207 ,"num" : 1  },
 "208" : {"ID" : 208 ,"armyID" : 208 ,"num" : 1  },
 "209" : {"ID" : 209 ,"armyID" : 209 ,"num" : 1  },
 "101" : {"ID" : 101 ,"armyID" : 101 ,"num" : 1  },
 "102" : {"ID" : 102 ,"armyID" : 102 ,"num" : 1  },
 "103" : {"ID" : 103 ,"armyID" : 103 ,"num" : 1  },
 "104" : {"ID" : 104 ,"armyID" : 104 ,"num" : 1  },
 "105" : {"ID" : 105 ,"armyID" : 105 ,"num" : 1  },
 "106" : {"ID" : 106 ,"armyID" : 106 ,"num" : 1  },
 "107" : {"ID" : 107 ,"armyID" : 107 ,"num" : 1  },
 "108" : {"ID" : 108 ,"armyID" : 108 ,"num" : 1  },
 "109" : {"ID" : 109 ,"armyID" : 109 ,"num" : 1  }
}