{
 "11" : {"ID" : 11 ,"name" : "铁剑" ,"functionType" : 1 ,"quality" : 1 ,"isRarity" : 0 ,"partId" : 1 ,"upproperty" : 12 ,"fixproperty" : [] ,"suitId" : 0 ,"dropLvl" : 1 ,"eatedExp" : 0 ,"sellPrice" : 100  },
 "12" : {"ID" : 12 ,"name" : "皮甲" ,"functionType" : 1 ,"quality" : 1 ,"isRarity" : 0 ,"partId" : 2 ,"upproperty" : 11 ,"fixproperty" : [] ,"suitId" : 0 ,"dropLvl" : 1 ,"eatedExp" : 0 ,"sellPrice" : 100  },
 "13" : {"ID" : 13 ,"name" : "皮护手" ,"functionType" : 1 ,"quality" : 1 ,"isRarity" : 0 ,"partId" : 3 ,"upproperty" : 4 ,"fixproperty" : [] ,"suitId" : 0 ,"dropLvl" : 1 ,"eatedExp" : 0 ,"sellPrice" : 100  },
 "14" : {"ID" : 14 ,"name" : "皮靴" ,"functionType" : 1 ,"quality" : 1 ,"isRarity" : 0 ,"partId" : 4 ,"upproperty" : 5 ,"fixproperty" : [] ,"suitId" : 0 ,"dropLvl" : 1 ,"eatedExp" : 0 ,"sellPrice" : 100  },
 "15" : {"ID" : 15 ,"name" : "匕首" ,"functionType" : 1 ,"quality" : 1 ,"isRarity" : 0 ,"partId" : 5 ,"upproperty" : 6 ,"fixproperty" : [] ,"suitId" : 0 ,"dropLvl" : 1 ,"eatedExp" : 0 ,"sellPrice" : 100  },
 "16" : {"ID" : 16 ,"name" : "皮头盔" ,"functionType" : 1 ,"quality" : 1 ,"isRarity" : 0 ,"partId" : 6 ,"upproperty" : 7 ,"fixproperty" : [] ,"suitId" : 0 ,"dropLvl" : 1 ,"eatedExp" : 0 ,"sellPrice" : 100  },
 "21" : {"ID" : 21 ,"name" : "铁剑" ,"functionType" : 1 ,"quality" : 2 ,"isRarity" : 0 ,"partId" : 1 ,"upproperty" : 12 ,"fixproperty" : [] ,"suitId" : 0 ,"dropLvl" : 1 ,"eatedExp" : 0 ,"sellPrice" : 200  },
 "22" : {"ID" : 22 ,"name" : "皮甲" ,"functionType" : 1 ,"quality" : 2 ,"isRarity" : 0 ,"partId" : 2 ,"upproperty" : 11 ,"fixproperty" : [] ,"suitId" : 0 ,"dropLvl" : 1 ,"eatedExp" : 0 ,"sellPrice" : 200  },
 "23" : {"ID" : 23 ,"name" : "皮护手" ,"functionType" : 1 ,"quality" : 2 ,"isRarity" : 0 ,"partId" : 3 ,"upproperty" : 4 ,"fixproperty" : [] ,"suitId" : 0 ,"dropLvl" : 1 ,"eatedExp" : 0 ,"sellPrice" : 200  },
 "24" : {"ID" : 24 ,"name" : "皮靴" ,"functionType" : 1 ,"quality" : 2 ,"isRarity" : 0 ,"partId" : 4 ,"upproperty" : 5 ,"fixproperty" : [] ,"suitId" : 0 ,"dropLvl" : 1 ,"eatedExp" : 0 ,"sellPrice" : 200  },
 "25" : {"ID" : 25 ,"name" : "匕首" ,"functionType" : 1 ,"quality" : 2 ,"isRarity" : 0 ,"partId" : 5 ,"upproperty" : 6 ,"fixproperty" : [] ,"suitId" : 0 ,"dropLvl" : 1 ,"eatedExp" : 0 ,"sellPrice" : 200  },
 "26" : {"ID" : 26 ,"name" : "皮盔" ,"functionType" : 1 ,"quality" : 2 ,"isRarity" : 0 ,"partId" : 6 ,"upproperty" : 7 ,"fixproperty" : [] ,"suitId" : 0 ,"dropLvl" : 1 ,"eatedExp" : 0 ,"sellPrice" : 200  },
 "31" : {"ID" : 31 ,"name" : "铁剑" ,"functionType" : 1 ,"quality" : 3 ,"isRarity" : 0 ,"partId" : 1 ,"upproperty" : 12 ,"fixproperty" : [] ,"suitId" : 1 ,"dropLvl" : 1 ,"eatedExp" : 0 ,"sellPrice" : 400  },
 "32" : {"ID" : 32 ,"name" : "皮甲" ,"functionType" : 1 ,"quality" : 3 ,"isRarity" : 0 ,"partId" : 2 ,"upproperty" : 11 ,"fixproperty" : [] ,"suitId" : 1 ,"dropLvl" : 1 ,"eatedExp" : 0 ,"sellPrice" : 400  },
 "33" : {"ID" : 33 ,"name" : "皮护手" ,"functionType" : 1 ,"quality" : 3 ,"isRarity" : 0 ,"partId" : 3 ,"upproperty" : 4 ,"fixproperty" : [] ,"suitId" : 1 ,"dropLvl" : 1 ,"eatedExp" : 0 ,"sellPrice" : 400  },
 "34" : {"ID" : 34 ,"name" : "皮靴" ,"functionType" : 1 ,"quality" : 3 ,"isRarity" : 0 ,"partId" : 4 ,"upproperty" : 5 ,"fixproperty" : [] ,"suitId" : 1 ,"dropLvl" : 1 ,"eatedExp" : 0 ,"sellPrice" : 400  },
 "35" : {"ID" : 35 ,"name" : "匕首" ,"functionType" : 1 ,"quality" : 3 ,"isRarity" : 0 ,"partId" : 5 ,"upproperty" : 6 ,"fixproperty" : [] ,"suitId" : 1 ,"dropLvl" : 1 ,"eatedExp" : 0 ,"sellPrice" : 400  },
 "36" : {"ID" : 36 ,"name" : "皮盔" ,"functionType" : 1 ,"quality" : 3 ,"isRarity" : 0 ,"partId" : 6 ,"upproperty" : 7 ,"fixproperty" : [] ,"suitId" : 1 ,"dropLvl" : 1 ,"eatedExp" : 0 ,"sellPrice" : 400  },
 "41" : {"ID" : 41 ,"name" : "龙鳞枪" ,"functionType" : 1 ,"quality" : 4 ,"isRarity" : 1 ,"partId" : 1 ,"upproperty" : 12 ,"fixproperty" : [] ,"suitId" : 2 ,"dropLvl" : 1 ,"eatedExp" : 0 ,"sellPrice" : 1000  },
 "42" : {"ID" : 42 ,"name" : "龙鳞铠" ,"functionType" : 1 ,"quality" : 4 ,"isRarity" : 1 ,"partId" : 2 ,"upproperty" : 11 ,"fixproperty" : [] ,"suitId" : 2 ,"dropLvl" : 1 ,"eatedExp" : 0 ,"sellPrice" : 1000  },
 "43" : {"ID" : 43 ,"name" : "龙鳞护手" ,"functionType" : 1 ,"quality" : 4 ,"isRarity" : 1 ,"partId" : 3 ,"upproperty" : 4 ,"fixproperty" : [] ,"suitId" : 2 ,"dropLvl" : 1 ,"eatedExp" : 0 ,"sellPrice" : 1000  },
 "44" : {"ID" : 44 ,"name" : "龙鳞靴" ,"functionType" : 1 ,"quality" : 4 ,"isRarity" : 1 ,"partId" : 4 ,"upproperty" : 5 ,"fixproperty" : [] ,"suitId" : 2 ,"dropLvl" : 1 ,"eatedExp" : 0 ,"sellPrice" : 1000  },
 "45" : {"ID" : 45 ,"name" : "龙牙匕首" ,"functionType" : 1 ,"quality" : 4 ,"isRarity" : 1 ,"partId" : 5 ,"upproperty" : 6 ,"fixproperty" : [] ,"suitId" : 2 ,"dropLvl" : 1 ,"eatedExp" : 0 ,"sellPrice" : 1000  },
 "46" : {"ID" : 46 ,"name" : "龙鳞盔" ,"functionType" : 1 ,"quality" : 4 ,"isRarity" : 1 ,"partId" : 6 ,"upproperty" : 7 ,"fixproperty" : [] ,"suitId" : 2 ,"dropLvl" : 1 ,"eatedExp" : 0 ,"sellPrice" : 1000  },
 "51" : {"ID" : 51 ,"name" : "麒麟刀" ,"functionType" : 1 ,"quality" : 4 ,"isRarity" : 1 ,"partId" : 1 ,"upproperty" : 12 ,"fixproperty" : [] ,"suitId" : 2 ,"dropLvl" : 1 ,"eatedExp" : 0 ,"sellPrice" : 1000  },
 "52" : {"ID" : 52 ,"name" : "麒麟铠" ,"functionType" : 1 ,"quality" : 4 ,"isRarity" : 1 ,"partId" : 2 ,"upproperty" : 11 ,"fixproperty" : [] ,"suitId" : 2 ,"dropLvl" : 1 ,"eatedExp" : 0 ,"sellPrice" : 1000  },
 "53" : {"ID" : 53 ,"name" : "麒麟护手" ,"functionType" : 1 ,"quality" : 4 ,"isRarity" : 1 ,"partId" : 3 ,"upproperty" : 4 ,"fixproperty" : [] ,"suitId" : 2 ,"dropLvl" : 1 ,"eatedExp" : 0 ,"sellPrice" : 1000  },
 "54" : {"ID" : 54 ,"name" : "麒麟靴" ,"functionType" : 1 ,"quality" : 4 ,"isRarity" : 1 ,"partId" : 4 ,"upproperty" : 5 ,"fixproperty" : [] ,"suitId" : 2 ,"dropLvl" : 1 ,"eatedExp" : 0 ,"sellPrice" : 1000  },
 "55" : {"ID" : 55 ,"name" : "麒麟护臂" ,"functionType" : 1 ,"quality" : 4 ,"isRarity" : 1 ,"partId" : 5 ,"upproperty" : 6 ,"fixproperty" : [] ,"suitId" : 2 ,"dropLvl" : 1 ,"eatedExp" : 0 ,"sellPrice" : 1000  },
 "56" : {"ID" : 56 ,"name" : "麒麟盔" ,"functionType" : 1 ,"quality" : 4 ,"isRarity" : 1 ,"partId" : 6 ,"upproperty" : 7 ,"fixproperty" : [] ,"suitId" : 2 ,"dropLvl" : 1 ,"eatedExp" : 0 ,"sellPrice" : 1000  },
 "61" : {"ID" : 61 ,"name" : "凤羽弓" ,"functionType" : 1 ,"quality" : 4 ,"isRarity" : 1 ,"partId" : 1 ,"upproperty" : 12 ,"fixproperty" : [] ,"suitId" : 2 ,"dropLvl" : 1 ,"eatedExp" : 0 ,"sellPrice" : 1000  },
 "62" : {"ID" : 62 ,"name" : "凤翅甲" ,"functionType" : 1 ,"quality" : 4 ,"isRarity" : 1 ,"partId" : 2 ,"upproperty" : 11 ,"fixproperty" : [] ,"suitId" : 2 ,"dropLvl" : 1 ,"eatedExp" : 0 ,"sellPrice" : 1000  },
 "63" : {"ID" : 63 ,"name" : "凤翎护手" ,"functionType" : 1 ,"quality" : 4 ,"isRarity" : 1 ,"partId" : 3 ,"upproperty" : 4 ,"fixproperty" : [] ,"suitId" : 2 ,"dropLvl" : 1 ,"eatedExp" : 0 ,"sellPrice" : 1000  },
 "64" : {"ID" : 64 ,"name" : "凤尾靴" ,"functionType" : 1 ,"quality" : 4 ,"isRarity" : 1 ,"partId" : 4 ,"upproperty" : 5 ,"fixproperty" : [] ,"suitId" : 2 ,"dropLvl" : 1 ,"eatedExp" : 0 ,"sellPrice" : 1000  },
 "65" : {"ID" : 65 ,"name" : "凤焰箭矢" ,"functionType" : 1 ,"quality" : 4 ,"isRarity" : 1 ,"partId" : 5 ,"upproperty" : 6 ,"fixproperty" : [] ,"suitId" : 2 ,"dropLvl" : 1 ,"eatedExp" : 0 ,"sellPrice" : 1000  },
 "66" : {"ID" : 66 ,"name" : "凤冠盔" ,"functionType" : 1 ,"quality" : 4 ,"isRarity" : 1 ,"partId" : 6 ,"upproperty" : 7 ,"fixproperty" : [] ,"suitId" : 2 ,"dropLvl" : 1 ,"eatedExp" : 0 ,"sellPrice" : 1000  },
 "71" : {"ID" : 71 ,"name" : "神龙鳞枪" ,"functionType" : 1 ,"quality" : 5 ,"isRarity" : 1 ,"partId" : 1 ,"upproperty" : 12 ,"fixproperty" : [] ,"suitId" : 3 ,"dropLvl" : 1 ,"eatedExp" : 0 ,"sellPrice" : 2000  },
 "72" : {"ID" : 72 ,"name" : "神龙鳞铠" ,"functionType" : 1 ,"quality" : 5 ,"isRarity" : 1 ,"partId" : 2 ,"upproperty" : 11 ,"fixproperty" : [] ,"suitId" : 3 ,"dropLvl" : 1 ,"eatedExp" : 0 ,"sellPrice" : 2000  },
 "73" : {"ID" : 73 ,"name" : "神龙鳞护手" ,"functionType" : 1 ,"quality" : 5 ,"isRarity" : 1 ,"partId" : 3 ,"upproperty" : 4 ,"fixproperty" : [] ,"suitId" : 3 ,"dropLvl" : 1 ,"eatedExp" : 0 ,"sellPrice" : 2000  },
 "74" : {"ID" : 74 ,"name" : "神龙鳞靴" ,"functionType" : 1 ,"quality" : 5 ,"isRarity" : 1 ,"partId" : 4 ,"upproperty" : 5 ,"fixproperty" : [] ,"suitId" : 3 ,"dropLvl" : 1 ,"eatedExp" : 0 ,"sellPrice" : 2000  },
 "75" : {"ID" : 75 ,"name" : "神龙牙匕首" ,"functionType" : 1 ,"quality" : 5 ,"isRarity" : 1 ,"partId" : 5 ,"upproperty" : 6 ,"fixproperty" : [] ,"suitId" : 3 ,"dropLvl" : 1 ,"eatedExp" : 0 ,"sellPrice" : 2000  },
 "76" : {"ID" : 76 ,"name" : "神龙鳞盔" ,"functionType" : 1 ,"quality" : 5 ,"isRarity" : 1 ,"partId" : 6 ,"upproperty" : 7 ,"fixproperty" : [] ,"suitId" : 3 ,"dropLvl" : 1 ,"eatedExp" : 0 ,"sellPrice" : 2000  },
 "101" : {"ID" : 101 ,"name" : "装备经验[50]" ,"functionType" : 2 ,"quality" : 1 ,"isRarity" : 0 ,"partId" : 0 ,"upproperty" : 0 ,"fixproperty" : [] ,"suitId" : 0 ,"dropLvl" : 1 ,"eatedExp" : 50 ,"sellPrice" : 100  },
 "102" : {"ID" : 102 ,"name" : "装备经验[100]" ,"functionType" : 2 ,"quality" : 2 ,"isRarity" : 0 ,"partId" : 0 ,"upproperty" : 0 ,"fixproperty" : [] ,"suitId" : 0 ,"dropLvl" : 1 ,"eatedExp" : 100 ,"sellPrice" : 100  },
 "103" : {"ID" : 103 ,"name" : "装备经验[200]" ,"functionType" : 2 ,"quality" : 2 ,"isRarity" : 0 ,"partId" : 0 ,"upproperty" : 0 ,"fixproperty" : [] ,"suitId" : 0 ,"dropLvl" : 1 ,"eatedExp" : 200 ,"sellPrice" : 100  },
 "104" : {"ID" : 104 ,"name" : "装备经验[500]" ,"functionType" : 2 ,"quality" : 3 ,"isRarity" : 0 ,"partId" : 0 ,"upproperty" : 0 ,"fixproperty" : [] ,"suitId" : 0 ,"dropLvl" : 1 ,"eatedExp" : 500 ,"sellPrice" : 100  },
 "105" : {"ID" : 105 ,"name" : "装备经验[1K]" ,"functionType" : 2 ,"quality" : 3 ,"isRarity" : 0 ,"partId" : 0 ,"upproperty" : 0 ,"fixproperty" : [] ,"suitId" : 0 ,"dropLvl" : 1 ,"eatedExp" : 1000 ,"sellPrice" : 100  },
 "106" : {"ID" : 106 ,"name" : "装备经验[2K]" ,"functionType" : 2 ,"quality" : 4 ,"isRarity" : 0 ,"partId" : 0 ,"upproperty" : 0 ,"fixproperty" : [] ,"suitId" : 0 ,"dropLvl" : 1 ,"eatedExp" : 2000 ,"sellPrice" : 100  },
 "107" : {"ID" : 107 ,"name" : "装备经验[5K]" ,"functionType" : 2 ,"quality" : 4 ,"isRarity" : 0 ,"partId" : 0 ,"upproperty" : 0 ,"fixproperty" : [] ,"suitId" : 0 ,"dropLvl" : 1 ,"eatedExp" : 5000 ,"sellPrice" : 100  },
 "108" : {"ID" : 108 ,"name" : "装备经验[10K]" ,"functionType" : 2 ,"quality" : 5 ,"isRarity" : 0 ,"partId" : 0 ,"upproperty" : 0 ,"fixproperty" : [] ,"suitId" : 0 ,"dropLvl" : 1 ,"eatedExp" : 10000 ,"sellPrice" : 100  },
 "109" : {"ID" : 109 ,"name" : "装备经验[800]" ,"functionType" : 2 ,"quality" : 3 ,"isRarity" : 0 ,"partId" : 0 ,"upproperty" : 0 ,"fixproperty" : [] ,"suitId" : 0 ,"dropLvl" : 1 ,"eatedExp" : 800 ,"sellPrice" : 100  },
 "110" : {"ID" : 110 ,"name" : "装备经验[1K2]" ,"functionType" : 2 ,"quality" : 3 ,"isRarity" : 0 ,"partId" : 0 ,"upproperty" : 0 ,"fixproperty" : [] ,"suitId" : 0 ,"dropLvl" : 1 ,"eatedExp" : 1200 ,"sellPrice" : 100  },
 "501" : {"ID" : 501 ,"name" : "白色装备" ,"functionType" : 3 ,"quality" : 1 ,"isRarity" : 0 ,"partId" : 0 ,"upproperty" : 0 ,"fixproperty" : [] ,"suitId" : 0 ,"dropLvl" : 1 ,"eatedExp" : 1 ,"sellPrice" : 1  },
 "502" : {"ID" : 502 ,"name" : "绿色装备" ,"functionType" : 3 ,"quality" : 2 ,"isRarity" : 0 ,"partId" : 0 ,"upproperty" : 0 ,"fixproperty" : [] ,"suitId" : 0 ,"dropLvl" : 1 ,"eatedExp" : 1 ,"sellPrice" : 1  },
 "503" : {"ID" : 503 ,"name" : "蓝色装备" ,"functionType" : 3 ,"quality" : 3 ,"isRarity" : 0 ,"partId" : 0 ,"upproperty" : 0 ,"fixproperty" : [] ,"suitId" : 0 ,"dropLvl" : 1 ,"eatedExp" : 1 ,"sellPrice" : 1  },
 "504" : {"ID" : 504 ,"name" : "紫色装备" ,"functionType" : 3 ,"quality" : 4 ,"isRarity" : 0 ,"partId" : 0 ,"upproperty" : 0 ,"fixproperty" : [] ,"suitId" : 0 ,"dropLvl" : 1 ,"eatedExp" : 1 ,"sellPrice" : 1  },
 "505" : {"ID" : 505 ,"name" : "蓝色装备" ,"functionType" : 3 ,"quality" : 3 ,"isRarity" : 0 ,"partId" : 0 ,"upproperty" : 0 ,"fixproperty" : [] ,"suitId" : 0 ,"dropLvl" : 1 ,"eatedExp" : 1 ,"sellPrice" : 1  },
 "506" : {"ID" : 506 ,"name" : "蓝色装备" ,"functionType" : 3 ,"quality" : 3 ,"isRarity" : 0 ,"partId" : 0 ,"upproperty" : 0 ,"fixproperty" : [] ,"suitId" : 0 ,"dropLvl" : 1 ,"eatedExp" : 1 ,"sellPrice" : 1  },
 "507" : {"ID" : 507 ,"name" : "蓝色装备" ,"functionType" : 3 ,"quality" : 3 ,"isRarity" : 0 ,"partId" : 0 ,"upproperty" : 0 ,"fixproperty" : [] ,"suitId" : 0 ,"dropLvl" : 1 ,"eatedExp" : 1 ,"sellPrice" : 1  },
 "508" : {"ID" : 508 ,"name" : "紫色装备" ,"functionType" : 3 ,"quality" : 4 ,"isRarity" : 0 ,"partId" : 0 ,"upproperty" : 0 ,"fixproperty" : [] ,"suitId" : 0 ,"dropLvl" : 1 ,"eatedExp" : 1 ,"sellPrice" : 1  },
 "509" : {"ID" : 509 ,"name" : "紫色装备" ,"functionType" : 3 ,"quality" : 4 ,"isRarity" : 0 ,"partId" : 0 ,"upproperty" : 0 ,"fixproperty" : [] ,"suitId" : 0 ,"dropLvl" : 1 ,"eatedExp" : 1 ,"sellPrice" : 1  },
 "510" : {"ID" : 510 ,"name" : "紫色装备" ,"functionType" : 3 ,"quality" : 4 ,"isRarity" : 0 ,"partId" : 0 ,"upproperty" : 0 ,"fixproperty" : [] ,"suitId" : 0 ,"dropLvl" : 1 ,"eatedExp" : 1 ,"sellPrice" : 1  }
}